{
"hud_line1":"漢化：嵐兮雨汐 町城安裡 蔽月八雲\n　　　淺夏 甘蔗醬\n\n程式：永久告別 船長唱擱淺",
"hud_line2":"淺夏的個人博客：https://sennatsu.com/",
"hud_line2_url":"https://sennatsu.com/",
"hud_line3":"我們的論壇：https://bbs.sennatsu.com/",
"hud_line3_url":"https://bbs.sennatsu.com/",
"hud_line4":"我們的QQ群：550817506",
"hud_line4_url":"https://jq.qq.com/?_wv=1027&k=5NSvUuQ",
"elf_name_0":"亞里莎",
"elf_name_1":"塞爾溫",
"elf_name_2":"嘉米懷特",
"elf_name_3":"衛宮士郎",
"elf_name_4":"阿莉雅",
"loyal_name_0":"艾莉卡",
"loyal_name_1":"萊瑟姆",
"loyal_name_2":"春麗",
"loyal_name_3":"庫丘林",
"loyal_name_4":"阿爾貝爾",
"witch_name_0":"伊莎貝爾",
"witch_name_1":"伊拉斯謨",
"witch_name_2":"韓蛛俐",
"witch_name_3":"遠阪凜",
"witch_name_4":"多蘿茜",
"dragon_name_0":"羅文",
"dragon_name_1":"法露特",
"dragon_name_2":"隆",
"dragon_name_3":"阿爾托莉雅",
"dragon_name_4":"亞爾多斯",
"shadow_name_0":"露娜",
"shadow_name_1":"莫迪凱",
"shadow_name_2":"維加",
"shadow_name_3":"阿爾托莉雅",
"shadow_name_4":"刻爾柏洛絲",
"vampire_name_0":"尤里亞斯",
"vampire_name_1":"斑比",
"vampire_name_2":"巴羅克",
"vampire_name_3":"美杜莎",
"vampire_name_4":"艾瑟拉",
"holy_name_0":"伊莉絲",
"holy_name_1":"迦樓羅",
"holy_name_2":"神月卡琳",
"holy_name_3":"伊莉雅斯菲爾",
"holy_name_4":"拉米娜",
"portal_name_0":"伊昂",
"portal_name_1":"涅克薩斯",
"splash_text":"感謝使用淺夏影之詩漢化模組",
"ui_enable":"開啓",
"ui_disable":"關閉  ",
"ui_under_development":"暫未開放，敬請期待",
"ui_link_click":"點擊跳轉",
"ui_link_under_development":"暫未開放",
"ui_link_join":"點擊加入",
"setting_tab_1_text_1":"*文本語言 ",
"setting_tab_1_text_2":"簡體中文",
"setting_tab_1_text_3":"繁體中文",
"setting_tab_1_text_4":"*文本字體 ",
"setting_tab_1_text_5":"繁體默認",
"setting_tab_1_text_6":"簡體默認",
"setting_tab_1_text_7":"方正隸變",
"setting_tab_1_text_8":"錄影顯示手牌",
"setting_tab_1_text_9":"閃卡全收集 ",
"setting_tab_1_text_10":"屏蔽對手皮膚",
"setting_tab_1_text_11":"手牌全閃卡 ",
"setting_tab_1_text_12":"稀有卡背  ",
"setting_tab_1_text_13":"普通虹變異畫",
"setting_tab_1_text_14":"注意：帶有*標識的設置項需重啓遊戲才能生效",
"setting_tab_1_text_15":"主頁背景  ",
"setting_tab_1_text_16":"系統預設",
"setting_tab_1_text_17":"碧藍幻想",
"setting_tab_1_text_18":"卡牌臺詞  ",
"setting_tab_1_text_19":"*卡牌名稱 ",
"setting_tab_1_text_20":"淺夏版本",
"setting_tab_1_text_21":"官方繁中",
"setting_tab_1_text_22":"優化卡牌分解",
"setting_tab_2_nochange":"不改變   ",
"setting_tab_2_text_1":"精靈    ",
"setting_tab_2_text_2":"塞爾溫 ",
"setting_tab_2_text_3":"嘉米懷特",
"setting_tab_2_text_4":"衛宮士郎",
"setting_tab_2_text_5":"皇室護衛  ",
"setting_tab_2_text_6":"萊瑟姆 ",
"setting_tab_2_text_7":"春麗  ",
"setting_tab_2_text_8":"庫丘林 ",
"setting_tab_2_text_9":"阿爾貝爾",
"setting_tab_2_text_10":"巫師    ",
"setting_tab_2_text_11":"伊拉斯謨",
"setting_tab_2_text_12":"韓蛛俐 ",
"setting_tab_2_text_13":"遠阪凜 ",
"setting_tab_2_text_14":"多蘿茜 ",
"setting_tab_2_text_15":"竜     ",
"setting_tab_2_text_16":"法露特 ",
"setting_tab_2_text_17":"隆  ",
"setting_tab_2_text_18":"阿爾托莉雅",
"setting_tab_2_text_19":"亞爾多斯",
"setting_tab_2_text_20":"死靈術士  ",
"setting_tab_2_text_21":"莫迪凱 ",
"setting_tab_2_text_22":"維加 ",
"setting_tab_2_text_23":"阿爾托莉雅",
"setting_tab_2_text_24":"刻爾柏洛絲",
"setting_tab_2_text_25":"吸血鬼  ",
"setting_tab_2_text_26":"斑比  ",
"setting_tab_2_text_27":"巴羅克 ",
"setting_tab_2_text_28":"美杜莎 ",
"setting_tab_2_text_29":"艾瑟拉 ",
"setting_tab_2_text_30":"主教    ",
"setting_tab_2_text_31":"迦樓羅 ",
"setting_tab_2_text_32":"神月卡琳",
"setting_tab_2_text_33":"伊莉雅斯菲爾",
"setting_tab_2_text_34":"皮膚選項會將預設英雄形象改變為所選皮膚形象",
"setting_tab_2_text_35":"阿莉雅 ",
"setting_tab_2_text_36":"拉米娜 ",
"setting_menu_text_1":"模組設置",
"setting_menu_text_2":"功能",
"setting_menu_text_3":"皮膚",
"setting_menu_text_4":"未開放",
"setting_menu_text_5":"未開放",
"setting_menu_text_6":"關於",
"two_pick_text_1":"*該評分資料來自2pick大神a1nsu，誰反對a神我們就……",
"two_pick_text_2":"暫無",
"ver_check_title_1":"發現新版本！",
"ver_check_title_2":"模組待更新！",
"confirm":"確定",
"ver_check_content_1":"模組有更新啦！最新版本{0}\n點擊確定跳轉網頁下載",
"ver_check_content_2":"本地檔案已更新！當前版本{0}\n請重新安裝模組",
"battle_helper_text_1":"己方牌庫",
"battle_helper_text_2":"對手出牌記錄",
"battle_helper_text_3":"對手職業數據",
"battle_helper_text_4":"當前模式下無法査看己方牌庫",
"battle_helper_text_5":"對方當前共鳴次數為{0}次\n",
"battle_helper_text_6":"簡",
"battle_helper_text_7":"原",
"battle_helper_text_8":"已",
"battle_helper_text_9":"敵",
"battle_helper_text_10":"職",
"battle_helper_text_11":"遠古造物",
"battle_helper_text_12":"神秘造物",
"battle_helper_text_13":"析界造物",
"battle_helper_text_14":"絢彩造物",
"battle_helper_text_15":"對方至多有{0}張{1}未打出\n",
"battle_helper_text_16":"對手手牌中的明牌",
"battle_helper_text_17":"思考時間：{0}秒",
"battle_helper_text_18":"無",
"battle_helper_text_19":"效",
"battle_helper_text_20":"對方牌庫",
"master_rank_text_0":"低保"
}